{"version":"0.0.1","name":"prettyLittleThing","dependencies":{"@react-native-community/cli":{"version":"11.3.0"},"@react-navigation/native-stack":{"version":"6.9.12"},"@react-navigation/native":{"version":"6.1.6"},"@reduxjs/toolkit":{"version":"1.9.5"},"axios-mock-adapter":{"version":"1.21.4"},"axios":{"version":"1.4.0"},"react-dom":{"version":"18.2.0"},"react-native-eject":{"version":"0.2.0"},"react-native-fast-image":{"version":"8.6.3"},"react-native-safe-area-context":{"version":"4.5.3"},"react-native-screens":{"version":"3.20.0"},"react-native":{"version":"0.71.7"},"react-redux":{"version":"8.0.5"},"react":{"version":"18.2.0"}}}